instagpy/__init__.py
instagpy/config.py
instagpy/instagpy.py
instagpy/path.py
instagpy/request_util.py
instagpy/session_util.py
instagpy/utils.py
instagpy-0.1.15.dist-info/LICENSE
instagpy-0.1.15.dist-info/METADATA
instagpy-0.1.15.dist-info/WHEEL
instagpy-0.1.15.dist-info/top_level.txt
instagpy-0.1.15.dist-info/RECORD
