Metadata-Version: 2.1
Name: instagpy
Version: 0.1.15
Summary: InstaGPy is an Instagram Unofficial API to extract data from Instargam Profiles. Scrape data from user's profile like username, userid, bio, email, phone, followers/followings list, profile media, account_type, etc.
Home-page: https://github.com/iSarabjitDhiman/InstaGPy
Author: Sarabjit Dhiman
Author-email: hello@sarabjitdhiman.com
License: MIT
Keywords: instagpy,instagram scraper,instagram email scraper,insta data extraction,instagram api,instagram python
Classifier: Development Status :: 3 - Alpha
Classifier: Intended Audience :: End Users/Desktop
Classifier: Intended Audience :: Developers
Classifier: Operating System :: Microsoft :: Windows
Classifier: Operating System :: MacOS :: MacOS X
Classifier: Operating System :: Unix
Classifier: License :: OSI Approved :: MIT License
Classifier: Topic :: Software Development :: Build Tools
Classifier: Programming Language :: Python :: 3
Requires-Python: >=3
License-File: LICENSE
Requires-Dist: beautifulsoup4
Requires-Dist: bs4
Requires-Dist: certifi
Requires-Dist: emoji
Requires-Dist: lxml
Requires-Dist: PySocks
Requires-Dist: requests
Requires-Dist: urllib3
